{"symbol":"A/HRC/RES/54/1","symbol_type":"A/HRC","resolution_number":"54/1.","title":"Situation of human rights in Afghanistan","session":"Fifty-fourth session","session_start_date":"11 September","session_end_date":"13 October 2023","adoption_meeting":"46th meeting","adoption_date":"11 October 2023","draft_resolution":"A/HRC/54/L.16","agenda_item":"Agenda item 2","agenda_item_name":"Annual report of the United Nations High Commissioner for Human Rights and reports of the Office of the  High Commissioner and the Secretary-General","sponsors":["ALBANIA","ANDORRA","AUSTRALIA","AUSTRIA","BELGIUM","BULGARIA","CANADA","CHILE","COSTA RICA","CROATIA","CYPRUS","CZECHIA","DENMARK","ECUADOR","ESTONIA","FINLAND","FRANCE","GERMANY","GREECE","HUNGARY","ICELAND","IRELAND","ISRAEL","ITALY","LATVIA","LIECHTENSTEIN","LITHUANIA","LUXEMBOURG","MALTA","MONACO","MONTENEGRO","NETHERLANDS (KINGDOM OF THE)","NEW ZEALAND","NORTH MACEDONIA","NORWAY","POLAND","PORTUGAL","ROMANIA","SLOVAKIA","SLOVENIA","SPAIN","SWEDEN","SWITZERLAND","UKRAINE","UNITED KINGDOM","UNITED STATES"],"additional_sponsors":[],"voting_type":"adoptedWithoutVote","SDGs":[],"MS_in_favour":[],"MS_against":[],"MS_abstaining":[],"MS_in_favour_count":"0","MS_against_count":"0","MS_abstaining_count":"0","adoption_type":"Without a vote","subjects":[["UN. Human Rights Council. Special Rapporteur on the Situation of Human Rights in Afghanistan","DHLAUTH"],["HUMAN RIGHTS","UNBIS Thesaurus"],["AFGHANISTAN","UNBIS Thesaurus"],["HUMAN RIGHTS VIOLATIONS","UNBIS Thesaurus"],["ACCOUNTABILITY","UNBIS Thesaurus"],["WOMEN'S RIGHTS","UNBIS Thesaurus"],["SPECIAL RAPPORTEURS","UNBIS Thesaurus"],["GENDER DISCRIMINATION","UNBIS Thesaurus"],["RESOURCES ALLOCATION","UNBIS Thesaurus"],["2","A/HRC/54/1"]]}"
"{"symbol":"A/HRC/RES/54/2","symbol_type":"A/HRC","resolution_number":"54/2.","title":"Responding to the human rights and humanitarian crisis caused by the ongoing armed conflict in the Sudan","session":"Fifty-fourth session","session_start_date":"11 September","session_end_date":"13 October 2023","adoption_meeting":"46th meeting","adoption_date":"11 October 2023","draft_resolution":"A/HRC/54/L.18","agenda_item":"Agenda item 2","agenda_item_name":"Annual report of the United Nations High Commissioner for Human Rights and reports of the Office of the  High Commissioner and the Secretary-General","sponsors":["ALBANIA","ANDORRA","BELGIUM","CZECHIA","DENMARK","ESTONIA","FINLAND","GERMANY","ICELAND","IRELAND","LATVIA","LIECHTENSTEIN","LITHUANIA","LUXEMBOURG","MALTA","MONACO","NETHERLANDS (KINGDOM OF THE)","NEW ZEALAND","NORTH MACEDONIA","NORWAY","POLAND","ROMANIA","SLOVAKIA","SLOVENIA","SWEDEN","UKRAINE","UNITED KINGDOM","UNITED STATES"],"additional_sponsors":[],"voting_type":"adoptedRecordedVote","SDGs":["16","3","5","11","2"],"MS_in_favour":["ARGENTINA","BELGIUM","CHILE","COSTA RICA","CZECHIA","FINLAND","FRANCE","GEORGIA","GERMANY","HONDURAS","LITHUANIA","LUXEMBOURG","MEXICO","MONTENEGRO","PARAGUAY","ROMANIA","UKRAINE","UNITED KINGDOM","UNITED STATES"],"MS_against":["ALGERIA","BOLIVIA (PLURINATIONAL STATE OF)","CHINA","CÔTE D'IVOIRE","CUBA","ERITREA","MALAYSIA","MALDIVES","MOROCCO","PAKISTAN","QATAR","SENEGAL","SOMALIA","SUDAN","UNITED ARAB EMIRATES","VIET NAM"],"MS_abstaining":["BANGLADESH","BENIN","CAMEROON","GABON","GAMBIA","INDIA","KAZAKHSTAN","KYRGYZSTAN","MALAWI","NEPAL","SOUTH AFRICA","UZBEKISTAN"],"MS_in_favour_count":"19","MS_against_count":"16","MS_abstaining_count":"12","adoption_type":"By a recorded vote","subjects":[["UN. Human Rights Council. Independent International Fact-Finding Mission for the Sudan","DHLAUTH"],["UN. Expert on Human Rights in the Sudan","DHLAUTH"],["HUMAN RIGHTS","UNBIS Thesaurus"],["HUMANITARIAN EMERGENCIES","UNBIS Thesaurus"],["SUDAN","UNBIS Thesaurus"],["HUMAN RIGHTS IN ARMED CONFLICTS","UNBIS Thesaurus"],["HUMAN RIGHTS VIOLATIONS","UNBIS Thesaurus"],["HUMANITARIAN ASSISTANCE","UNBIS Thesaurus"],["FACT-FINDING MISSIONS","UNBIS Thesaurus"],["EXPERTS","UNBIS Thesaurus"],["2","A/HRC/54/1"]]}"
"